{
  "$schema": "https://json-schema.org/draft/2020-12/schema",
  "additionalProperties": false,
  "properties": {
    "declared_at": {
      "type": "string"
    },
    "incident_id": {
      "type": "string"
    },
    "owner_id": {
      "type": "string"
    },
    "severity": {
      "type": "string"
    },
    "state": {
      "type": "string"
    },
    "summary": {
      "type": "string"
    }
  },
  "required": [
    "incident_id",
    "severity",
    "summary",
    "owner_id",
    "declared_at",
    "state"
  ],
  "title": "incident",
  "type": "object"
}
